loutilities/__init__.py
loutilities/agegrade.py
loutilities/apikey.py
loutilities/applytemplate.py
loutilities/bfile.py
loutilities/boolexpr.py
loutilities/config.py
loutilities/configparser.py
loutilities/csvu.py
loutilities/csvwt.py
loutilities/extconfigparser.py
loutilities/filetrigger.py
loutilities/filtercsv.py
loutilities/filters.py
loutilities/geo.py
loutilities/googleauth.py
loutilities/kmlutils.py
loutilities/makerst.py
loutilities/namesplitter.py
loutilities/nesteddict.py
loutilities/nicknames.csv
loutilities/nicknames.py
loutilities/renderrun.py
loutilities/sqlalchemy_helpers.py
loutilities/tables.py
loutilities/textreader.py
loutilities/timeu.py
loutilities/transform.py
loutilities/version.py
loutilities/wxextensions.py
loutilities/xmldict.py
loutilities/flask/__init__.py
loutilities/flask/user/__init__.py
loutilities/flask/user/views.py
loutilities/flask_helpers/__init__.py
loutilities/flask_helpers/as_blueprint.py
loutilities/flask_helpers/blueprints.py
loutilities/flask_helpers/decorators.py
loutilities/flask_helpers/mailer.py
loutilities/tables-assets/static/background-post-data-manager.js
loutilities/tables-assets/static/branding.css
loutilities/tables-assets/static/buttons.colvis.js
loutilities/tables-assets/static/charts.css
loutilities/tables-assets/static/charts.js
loutilities/tables-assets/static/datatables-childrow.js
loutilities/tables-assets/static/datatables.css
loutilities/tables-assets/static/datatables.dataRender.datetime.js
loutilities/tables-assets/static/datatables.dataRender.ellipsis.js
loutilities/tables-assets/static/datatables.dataRender.googledoc.js
loutilities/tables-assets/static/datatables.js
loutilities/tables-assets/static/editor-saeditor.js
loutilities/tables-assets/static/editor.buttons.editchildrowrefresh.js
loutilities/tables-assets/static/editor.buttons.editrefresh.js
loutilities/tables-assets/static/editor.buttons.separator.js
loutilities/tables-assets/static/editor.ckeditor5.js
loutilities-3.11.1.dist-info/METADATA
loutilities-3.11.1.dist-info/WHEEL
loutilities-3.11.1.dist-info/entry_points.txt
loutilities-3.11.1.dist-info/top_level.txt
loutilities-3.11.1.dist-info/RECORD
