Metadata-Version: 2.4
Name: loutilities
Version: 3.11.1
Summary: some hopefully useful utilities
Home-page: http://github.com/louking/loutilities
Author: Lou King
Author-email: lking@pobox.com
License: Apache License, Version 2.0
Requires-Dist: flask-security-too>=5.5.0
Requires-Dist: flask-sqlalchemy>=3.0.5
Dynamic: author
Dynamic: author-email
Dynamic: description
Dynamic: home-page
Dynamic: license
Dynamic: requires-dist
Dynamic: summary
